LICENSE.txt
MANIFEST.in
breakpoint.py
doctests.txt
setup.cfg
setup.py
test.py
breakpoint.egg-info/PKG-INFO
breakpoint.egg-info/SOURCES.txt
breakpoint.egg-info/dependency_links.txt
breakpoint.egg-info/top_level.txt
lib/easy_install.py
lib/easy_install.pyc
lib/pkg_resources.py
lib/pkg_resources.pyc
lib/sh.py
lib/sh.pyc
lib/_markerlib/__init__.py
lib/_markerlib/__init__.pyc
lib/_markerlib/markers.py
lib/_markerlib/markers.pyc
lib/about/__init__.py
lib/about/__init__.pyc
lib/about/about.py
lib/about/about.pyc
lib/about-4.0.1-py2.7.egg-info/PKG-INFO
lib/about-4.0.1-py2.7.egg-info/SOURCES.txt
lib/about-4.0.1-py2.7.egg-info/dependency_links.txt
lib/about-4.0.1-py2.7.egg-info/installed-files.txt
lib/about-4.0.1-py2.7.egg-info/requires.txt
lib/about-4.0.1-py2.7.egg-info/top_level.txt
lib/setuptools/__init__.py
lib/setuptools/__init__.pyc
lib/setuptools/archive_util.py
lib/setuptools/archive_util.pyc
lib/setuptools/cli-32.exe
lib/setuptools/cli-64.exe
lib/setuptools/cli-arm-32.exe
lib/setuptools/cli.exe
lib/setuptools/compat.py
lib/setuptools/compat.pyc
lib/setuptools/depends.py
lib/setuptools/depends.pyc
lib/setuptools/dist.py
lib/setuptools/dist.pyc
lib/setuptools/extension.py
lib/setuptools/extension.pyc
lib/setuptools/gui-32.exe
lib/setuptools/gui-64.exe
lib/setuptools/gui-arm-32.exe
lib/setuptools/gui.exe
lib/setuptools/lib2to3_ex.py
lib/setuptools/lib2to3_ex.pyc
lib/setuptools/msvc9_support.py
lib/setuptools/msvc9_support.pyc
lib/setuptools/package_index.py
lib/setuptools/package_index.pyc
lib/setuptools/py26compat.py
lib/setuptools/py26compat.pyc
lib/setuptools/py27compat.py
lib/setuptools/py27compat.pyc
lib/setuptools/py31compat.py
lib/setuptools/py31compat.pyc
lib/setuptools/sandbox.py
lib/setuptools/sandbox.pyc
lib/setuptools/script (dev).tmpl
lib/setuptools/script.tmpl
lib/setuptools/site-patch.py
lib/setuptools/site-patch.pyc
lib/setuptools/ssl_support.py
lib/setuptools/ssl_support.pyc
lib/setuptools/svn_utils.py
lib/setuptools/svn_utils.pyc
lib/setuptools/unicode_utils.py
lib/setuptools/unicode_utils.pyc
lib/setuptools/utils.py
lib/setuptools/utils.pyc
lib/setuptools/version.py
lib/setuptools/version.pyc
lib/setuptools/windows_support.py
lib/setuptools/windows_support.pyc
lib/setuptools-7.0.dist-info/DESCRIPTION.rst
lib/setuptools-7.0.dist-info/METADATA
lib/setuptools-7.0.dist-info/RECORD
lib/setuptools-7.0.dist-info/WHEEL
lib/setuptools-7.0.dist-info/dependency_links.txt
lib/setuptools-7.0.dist-info/entry_points.txt
lib/setuptools-7.0.dist-info/metadata.json
lib/setuptools-7.0.dist-info/top_level.txt
lib/setuptools-7.0.dist-info/zip-safe
lib/setuptools/command/__init__.py
lib/setuptools/command/__init__.pyc
lib/setuptools/command/alias.py
lib/setuptools/command/alias.pyc
lib/setuptools/command/bdist_egg.py
lib/sh-1.09-py2.7.egg-info/PKG-INFO
lib/sh-1.09-py2.7.egg-info/SOURCES.txt
lib/sh-1.09-py2.7.egg-info/dependency_links.txt
lib/sh-1.09-py2.7.egg-info/installed-files.txt
lib/sh-1.09-py2.7.egg-info/top_level.txt