Metadata-Version: 1.0
Name: breakpoint
Version: 2.1.3
Summary: Function Execution Tracker
Home-page: http://boisgera.github.io/breakpoint
Author: Sébastien Boisgérault
Author-email: Sebastien.Boisgerault@mines-paristech.fr
License: MIT License
Platform: UNKNOWN
